pybeans/ColorfulFormatter.py
pybeans/__init__.py
pybeans/app_tool.py
pybeans/config_sample.py
pybeans/exception.py
pybeans/get_ch.py
pybeans/utils.py
pybeans-1.13.6.dist-info/LICENSE
pybeans-1.13.6.dist-info/METADATA
pybeans-1.13.6.dist-info/WHEEL
pybeans-1.13.6.dist-info/top_level.txt
pybeans-1.13.6.dist-info/RECORD
