Metadata-Version: 2.1
Name: pybeans
Version: 1.13.6
Summary: Common toolkit for python.
Home-page: https://github.com/chariothy/pybeans.git
Author: Henry TIAN
Author-email: chariothy@gmail.com
License: MIT
Classifier: License :: OSI Approved :: MIT License
Classifier: Programming Language :: Python
Classifier: Programming Language :: Python :: 3.8
Classifier: Programming Language :: Python :: 3.9
Classifier: Programming Language :: Python :: 3.10
Classifier: Programming Language :: Python :: 3.11
Classifier: Programming Language :: Python :: 3.12
Classifier: Programming Language :: Python :: Implementation :: CPython
Requires-Python: >=3.8.0
License-File: LICENSE
Requires-Dist: colorama>=0.4.4
Requires-Dist: requests>=2.32.0
Requires-Dist: munch>=4.0.0
